MANIFEST.in
README.md
setup.py
dash_ui/__init__.py
dash_ui/controlpanel.py
dash_ui/grid.py
dash_ui/version.py
dash_ui.egg-info/PKG-INFO
dash_ui.egg-info/SOURCES.txt
dash_ui.egg-info/dependency_links.txt
dash_ui.egg-info/requires.txt
dash_ui.egg-info/top_level.txt