Metadata-Version: 1.0
Name: dash-ui
Version: 0.3.0
Summary: Some abstractions to make creating UIs easier in Dash.
Home-page: UNKNOWN
Author: Ryan rmarren1
Author-email: rymarr@tuta.io    
License: MIT
Platform: UNKNOWN
